async_pyfcm/__init__.py
async_pyfcm/async_pyfcm.py
async_pyfcm/errors.py
async_pyfcm/message.py
async_pyfcm/pyfcm_auth.py
async_pyfcm-0.1.4.dist-info/LICENSE
async_pyfcm-0.1.4.dist-info/METADATA
async_pyfcm-0.1.4.dist-info/WHEEL
async_pyfcm-0.1.4.dist-info/top_level.txt
async_pyfcm-0.1.4.dist-info/RECORD
