Metadata-Version: 2.1
Name: async-pyfcm
Version: 0.1.4
Summary: Python Asynchronous FCM Push Controller
Home-page: https://github.com/837477/async-pyfcm
Author: 837477
Author-email: 8374770@gmail.com
License: MIT License
Keywords: Python Asynchronous FCM Push Controller
Platform: any
Classifier: Intended Audience :: Developers
Classifier: License :: OSI Approved :: MIT License
Classifier: Operating System :: OS Independent
Classifier: Programming Language :: Python :: 3.7
Classifier: Programming Language :: Python :: 3.8
Classifier: Programming Language :: Python :: 3.9
Classifier: Programming Language :: Python :: 3.10
Classifier: Programming Language :: Python :: 3.11
Classifier: Programming Language :: Python :: 3.12
Classifier: Topic :: Internet :: WWW/HTTP :: Dynamic Content
Classifier: Topic :: Software Development :: Libraries :: Python Modules
License-File: LICENSE
Requires-Dist: requests
Requires-Dist: aiohttp
Requires-Dist: google-auth
